fmot/ENV_REQUIREMENTS.sh
fmot/ONNX2FQIR_REQUIREMENTS
fmot/PY_REQUIREMENTS
fmot/TF_REQUIREMENTS
fmot/VERSION
fmot/__init__.py
fmot/_open_docs.py
fmot/_supported_ops.py
fmot/configure.py
fmot/control.py
fmot/exceptions.py
fmot/execute_code.py
fmot/functional.py
fmot/iospec.py
fmot/precisions.py
fmot/stateful_sequencer.py
fmot/torchscript_utils.py
fmot/beta/__init__.py
fmot/beta/_quant_viz_example.py
fmot/beta/amp.py
fmot/beta/auto_multiprecision.py
fmot/beta/heirarchical_labeling.py
fmot/beta/quant_error_visualizer.py
fmot/beta/quantize_part.py
fmot/beta/signal24/__init__.py
fmot/beta/signal24/examples.py
fmot/beta/signal24/fft_decomp.py
fmot/beta/signal24/gmac_wrappers.py
fmot/beta/signal24/higher_precision_matmul.py
fmot/beta/signal24/stft.py
fmot/convert/__init__.py
fmot/convert/_convert_to_qat.py
fmot/convert/apply_tags.py
fmot/convert/conversion_api.py
fmot/convert/default_mappings.py
fmot/convert/default_patchings.py
fmot/convert/default_substitutions.py
fmot/convert/lut_registry.py
fmot/convert/mapping.py
fmot/convert/optimizer.py
fmot/convert/param_manager.py
fmot/convert/patch_ir.py
fmot/convert/patching.py
fmot/convert/prune_reparametrization.py
fmot/convert/quantizer_manager.py
fmot/convert/substitution.py
fmot/fqir/__init__.py
fmot/fqir/metadata.py
fmot/fqir/utils.py
fmot/fqir/graph_proto/__init__.py
fmot/fqir/graph_proto/graph_proto.py
fmot/fqir/graph_proto/graph_runtime.py
fmot/fqir/multigraph/__init__.py
fmot/fqir/multigraph/dynamic_parameter.py
fmot/fqir/nodes/__init__.py
fmot/fqir/nodes/node_base.py
fmot/fqir/nodes/node_proto.py
fmot/fqir/nodes/opcount.py
fmot/fqir/nodes/opcounters.py
fmot/fqir/nodes/optype_base.py
fmot/fqir/nodes/optypes.py
fmot/fqir/passes/__init__.py
fmot/fqir/passes/batchdim_removal.py
fmot/fqir/passes/cleanup.py
fmot/fqir/passes/conv1d_weight_pass.py
fmot/fqir/passes/dimtag_removal.py
fmot/fqir/passes/fold_reused_params.py
fmot/fqir/passes/helpers.py
fmot/fqir/passes/kernel_inlining.py
fmot/fqir/passes/kernelize_lstm.py
fmot-3.13.2.dist-info/licenses/LICENSE
fmot-3.13.2.dist-info/METADATA
fmot-3.13.2.dist-info/WHEEL
fmot-3.13.2.dist-info/top_level.txt
fmot-3.13.2.dist-info/RECORD
