Metadata-Version: 2.4
Name: fmot
Version: 3.13.2
Summary: Femtosense Model Optimization Toolkit
Home-page: https://github.com/femtosense/fmot
Author: Femtosense
Author-email: info@femtosense.ai
Project-URL: Source, https://github.com/femtosense/fmot
Classifier: Development Status :: 3 - Alpha
Classifier: Intended Audience :: Developers
Classifier: Programming Language :: Python :: 3.6
Classifier: Programming Language :: Python :: 3.7
Classifier: Programming Language :: Python :: 3.8
Classifier: Programming Language :: Python :: 3.9
Classifier: Programming Language :: Python :: 3.10
Classifier: Programming Language :: Python :: 3 :: Only
Classifier: Operating System :: OS Independent
Requires-Python: >=3.6
License-File: LICENSE
Requires-Dist: Cython
Requires-Dist: torch>=1.12.1
Requires-Dist: numpy>=2.0
Requires-Dist: scipy
Requires-Dist: python_speech_features
Requires-Dist: tqdm
Requires-Dist: networkx
Requires-Dist: deprecation
Requires-Dist: tabulate
Requires-Dist: colorcet
Requires-Dist: matplotlib
Requires-Dist: pandas
Requires-Dist: pyyaml
Requires-Dist: ordered_set==4.1.0
Requires-Dist: femtorun>=1.1.6
Provides-Extra: onnx2fqir
Requires-Dist: onnx; extra == "onnx2fqir"
Requires-Dist: onnxruntime; extra == "onnx2fqir"
Requires-Dist: tensorflow; extra == "onnx2fqir"
Provides-Extra: tf
Requires-Dist: tensorflow; extra == "tf"
Requires-Dist: tf-keras; extra == "tf"
Dynamic: author
Dynamic: author-email
Dynamic: classifier
Dynamic: description
Dynamic: description-content-type
Dynamic: home-page
Dynamic: license-file
Dynamic: project-url
Dynamic: provides-extra
Dynamic: requires-dist
Dynamic: requires-python
Dynamic: summary
